[
    {
        "a": "2024",
        "g": "M",
        "op": "c",
        "c": "0030",
        "p": 14706.0,
        "d": 14706.0,
        "i": 14706.0,
        "t": "1"
    },
    {
        "a": "2024",
        "g": "M",
        "op": "c",
        "c": "0036",
        "p": 13500.0,
        "d": 12948.0,
        "i": 12948.0,
        "t": "1"
    },
    {
        "a": "2024",
        "g": "M",
        "op": "c",
        "c": "0039",
        "p": 4000.0,
        "d": 1722.0,
        "i": 1722.0,
        "t": "1"
    },
    {
        "a": "2024",
        "g": "M",
        "op": "c",
        "c": "0040",
        "p": 4000.0,
        "d": 0.0,
        "i": 0.0,
        "t": "1"
    },
    {
        "a": "2024",
        "g": "M",
        "op": "c",
        "c": "0042",
        "p": 47170.0,
        "d": 21750.0,
        "i": 21750.0,
        "t": "1"
    },
    {
        "a": "2024",
        "g": "M",
        "op": "c",
        "c": "0068",
        "p": 18842.0,
        "d": 13600.0,
        "i": 13600.0,
        "t": "1"
    },
    {
        "a": "2024",
        "g": "M",
        "op": "c",
        "c": "0083",
        "p": 80763.0,
        "d": 61964.0,
        "i": 61964.0,
        "t": "1"
    },
    {
        "a": "2024",
        "g": "M",
        "op": "c",
        "c": "0090",
        "p": 95500.0,
        "d": 93297.0,
        "i": 93297.0,
        "t": "1"
    },
    {
        "a": "2024",
        "g": "M",
        "op": "c",
        "c": "0109",
        "p": 9578.0,
        "d": 0.0,
        "i": 0.0,
        "t": "1"
    },
    {
        "a": "2024",
        "g": "M",
        "op": "c",
        "c": "0148",
        "p": 135530.0,
        "d": 131567.0,
        "i": 131567.0,
        "t": "1"
    },
    {
        "a": "2024",
        "g": "M",
        "op": "f",
        "c": "03",
        "p": 855896.0,
        "d": 700321.0,
        "i": 698676.0,
        "t": "1"
    },
    {
        "a": "2024",
        "g": "M",
        "op": "f",
        "c": "05",
        "p": 33548.0,
        "d": 28306.0,
        "i": 28306.0,
        "t": "1"
    },
    {
        "a": "2024",
        "g": "M",
        "op": "f",
        "c": "07",
        "p": 396095.0,
        "d": 393931.0,
        "i": 393931.0,
        "t": "1"
    },
    {
        "a": "2024",
        "g": "M",
        "op": "f",
        "c": "08",
        "p": 722.0,
        "d": 720.0,
        "i": 720.0,
        "t": "1"
    },
    {
        "a": "2024",
        "g": "M",
        "op": "f",
        "c": "10",
        "p": 110170.0,
        "d": 46002.0,
        "i": 46002.0,
        "t": "1"
    },
    {
        "a": "2024",
        "g": "M",
        "op": "c",
        "c": "1001",
        "p": 1000.0,
        "d": 0.0,
        "i": 0.0,
        "t": "1"
    },
    {
        "a": "2024",
        "g": "M",
        "op": "f",
        "c": "15",
        "p": 135530.0,
        "d": 131567.0,
        "i": 131567.0,
        "t": "1"
    },
    {
        "a": "2024",
        "g": "M",
        "op": "f",
        "c": "16",
        "p": 43874.0,
        "d": 28355.0,
        "i": 26464.0,
        "t": "1"
    },
    {
        "a": "2024",
        "g": "M",
        "op": "f",
        "c": "17",
        "p": 32300.0,
        "d": 31566.0,
        "i": 31566.0,
        "t": "1"
    },
    {
        "a": "2024",
        "g": "M",
        "op": "f",
        "c": "18",
        "p": 80763.0,
        "d": 61964.0,
        "i": 61964.0,
        "t": "1"
    },
    {
        "a": "2024",
        "g": "M",
        "op": "f",
        "c": "19",
        "p": 9578.0,
        "d": 0.0,
        "i": 0.0,
        "t": "1"
    },
    {
        "a": "2024",
        "g": "M",
        "op": "f",
        "c": "20",
        "p": 4500.0,
        "d": 1440.0,
        "i": 1440.0,
        "t": "1"
    },
    {
        "a": "2024",
        "g": "M",
        "op": "f",
        "c": "21",
        "p": 29983.0,
        "d": 27538.0,
        "i": 27538.0,
        "t": "1"
    },
    {
        "a": "2024",
        "g": "M",
        "op": "f",
        "c": "22",
        "p": 115994.0,
        "d": 108452.0,
        "i": 108452.0,
        "t": "1"
    },
    {
        "a": "2024",
        "g": "M",
        "op": "f",
        "c": "23",
        "p": 26181.0,
        "d": 16136.0,
        "i": 16136.0,
        "t": "1"
    },
    {
        "a": "2024",
        "g": "M",
        "op": "c",
        "c": "9001",
        "p": 504749.0,
        "d": 381860.0,
        "i": 380215.0,
        "t": "1"
    },
    {
        "a": "2024",
        "g": "M",
        "op": "c",
        "c": "9002",
        "p": 945796.0,
        "d": 842883.0,
        "i": 840992.0,
        "t": "1"
    },
    {
        "a": "2024",
        "g": "M",
        "op": "c",
        "c": "0040",
        "p": 0.0,
        "d": 0.0,
        "i": 0.0,
        "t": "2"
    },
    {
        "a": "2024",
        "g": "M",
        "op": "c",
        "c": "0042",
        "p": 47170.0,
        "d": 21750.0,
        "i": 21750.0,
        "t": "2"
    },
    {
        "a": "2024",
        "g": "M",
        "op": "c",
        "c": "0083",
        "p": 57097.0,
        "d": 39600.0,
        "i": 39600.0,
        "t": "2"
    },
    {
        "a": "2024",
        "g": "M",
        "op": "c",
        "c": "0090",
        "p": 95500.0,
        "d": 93297.0,
        "i": 93297.0,
        "t": "2"
    },
    {
        "a": "2024",
        "g": "M",
        "op": "c",
        "c": "0109",
        "p": 9578.0,
        "d": 0.0,
        "i": 0.0,
        "t": "2"
    },
    {
        "a": "2024",
        "g": "M",
        "op": "c",
        "c": "0148",
        "p": 135530.0,
        "d": 131567.0,
        "i": 131567.0,
        "t": "2"
    },
    {
        "a": "2024",
        "g": "M",
        "op": "f",
        "c": "03",
        "p": 347107.0,
        "d": 315122.0,
        "i": 315122.0,
        "t": "2"
    },
    {
        "a": "2024",
        "g": "M",
        "op": "f",
        "c": "08",
        "p": 722.0,
        "d": 720.0,
        "i": 720.0,
        "t": "2"
    },
    {
        "a": "2024",
        "g": "M",
        "op": "f",
        "c": "10",
        "p": 102170.0,
        "d": 44280.0,
        "i": 44280.0,
        "t": "2"
    },
    {
        "a": "2024",
        "g": "M",
        "op": "f",
        "c": "15",
        "p": 135530.0,
        "d": 131567.0,
        "i": 131567.0,
        "t": "2"
    },
    {
        "a": "2024",
        "g": "M",
        "op": "f",
        "c": "18",
        "p": 57097.0,
        "d": 39600.0,
        "i": 39600.0,
        "t": "2"
    },
    {
        "a": "2024",
        "g": "M",
        "op": "f",
        "c": "19",
        "p": 9578.0,
        "d": 0.0,
        "i": 0.0,
        "t": "2"
    },
    {
        "a": "2024",
        "g": "M",
        "op": "f",
        "c": "22",
        "p": 95500.0,
        "d": 93297.0,
        "i": 93297.0,
        "t": "2"
    },
    {
        "a": "2024",
        "g": "M",
        "op": "c",
        "c": "9002",
        "p": 402829.0,
        "d": 338372.0,
        "i": 338372.0,
        "t": "2"
    },
    {
        "a": "2024",
        "g": "M",
        "op": "c",
        "c": "0030",
        "p": 14706.0,
        "d": 14706.0,
        "i": 14706.0,
        "t": "3"
    },
    {
        "a": "2024",
        "g": "M",
        "op": "c",
        "c": "0036",
        "p": 13500.0,
        "d": 12948.0,
        "i": 12948.0,
        "t": "3"
    },
    {
        "a": "2024",
        "g": "M",
        "op": "c",
        "c": "0039",
        "p": 4000.0,
        "d": 1722.0,
        "i": 1722.0,
        "t": "3"
    },
    {
        "a": "2024",
        "g": "M",
        "op": "c",
        "c": "0040",
        "p": 4000.0,
        "d": 0.0,
        "i": 0.0,
        "t": "3"
    },
    {
        "a": "2024",
        "g": "M",
        "op": "c",
        "c": "0068",
        "p": 18842.0,
        "d": 13600.0,
        "i": 13600.0,
        "t": "3"
    },
    {
        "a": "2024",
        "g": "M",
        "op": "c",
        "c": "0083",
        "p": 23666.0,
        "d": 22364.0,
        "i": 22364.0,
        "t": "3"
    },
    {
        "a": "2024",
        "g": "M",
        "op": "f",
        "c": "03",
        "p": 508789.0,
        "d": 385199.0,
        "i": 383555.0,
        "t": "3"
    },
    {
        "a": "2024",
        "g": "M",
        "op": "f",
        "c": "05",
        "p": 33548.0,
        "d": 28306.0,
        "i": 28306.0,
        "t": "3"
    },
    {
        "a": "2024",
        "g": "M",
        "op": "f",
        "c": "07",
        "p": 396095.0,
        "d": 393931.0,
        "i": 393931.0,
        "t": "3"
    },
    {
        "a": "2024",
        "g": "M",
        "op": "f",
        "c": "10",
        "p": 8000.0,
        "d": 1722.0,
        "i": 1722.0,
        "t": "3"
    },
    {
        "a": "2024",
        "g": "M",
        "op": "c",
        "c": "1001",
        "p": 1000.0,
        "d": 0.0,
        "i": 0.0,
        "t": "3"
    },
    {
        "a": "2024",
        "g": "M",
        "op": "f",
        "c": "16",
        "p": 43874.0,
        "d": 28355.0,
        "i": 26464.0,
        "t": "3"
    },
    {
        "a": "2024",
        "g": "M",
        "op": "f",
        "c": "17",
        "p": 32300.0,
        "d": 31566.0,
        "i": 31566.0,
        "t": "3"
    },
    {
        "a": "2024",
        "g": "M",
        "op": "f",
        "c": "18",
        "p": 23666.0,
        "d": 22364.0,
        "i": 22364.0,
        "t": "3"
    },
    {
        "a": "2024",
        "g": "M",
        "op": "f",
        "c": "20",
        "p": 4500.0,
        "d": 1440.0,
        "i": 1440.0,
        "t": "3"
    },
    {
        "a": "2024",
        "g": "M",
        "op": "f",
        "c": "21",
        "p": 29983.0,
        "d": 27538.0,
        "i": 27538.0,
        "t": "3"
    },
    {
        "a": "2024",
        "g": "M",
        "op": "f",
        "c": "22",
        "p": 20494.0,
        "d": 15155.0,
        "i": 15155.0,
        "t": "3"
    },
    {
        "a": "2024",
        "g": "M",
        "op": "f",
        "c": "23",
        "p": 26181.0,
        "d": 16136.0,
        "i": 16136.0,
        "t": "3"
    },
    {
        "a": "2024",
        "g": "M",
        "op": "c",
        "c": "9001",
        "p": 504749.0,
        "d": 381860.0,
        "i": 380215.0,
        "t": "3"
    },
    {
        "a": "2024",
        "g": "M",
        "op": "c",
        "c": "9002",
        "p": 542967.0,
        "d": 504511.0,
        "i": 502620.0,
        "t": "3"
    }
]