[
    {
        "a": "2024",
        "g": "M",
        "op": "c",
        "c": "0002",
        "p": 43718.0,
        "d": 31778.0,
        "i": 26378.0,
        "t": "1"
    },
    {
        "a": "2024",
        "g": "M",
        "op": "c",
        "c": "0030",
        "p": 373849.0,
        "d": 322824.0,
        "i": 312056.0,
        "t": "1"
    },
    {
        "a": "2024",
        "g": "M",
        "op": "c",
        "c": "0036",
        "p": 382494.0,
        "d": 298395.0,
        "i": 277527.0,
        "t": "1"
    },
    {
        "a": "2024",
        "g": "M",
        "op": "c",
        "c": "0042",
        "p": 2855805.0,
        "d": 1548243.0,
        "i": 1548243.0,
        "t": "1"
    },
    {
        "a": "2024",
        "g": "M",
        "op": "c",
        "c": "0046",
        "p": 0.0,
        "d": 0.0,
        "i": 0.0,
        "t": "1"
    },
    {
        "a": "2024",
        "g": "M",
        "op": "c",
        "c": "0068",
        "p": 306707.0,
        "d": 226713.0,
        "i": 171286.0,
        "t": "1"
    },
    {
        "a": "2024",
        "g": "M",
        "op": "c",
        "c": "0083",
        "p": 6892247.0,
        "d": 3012043.0,
        "i": 2662442.0,
        "t": "1"
    },
    {
        "a": "2024",
        "g": "M",
        "op": "c",
        "c": "0089",
        "p": 1353381.0,
        "d": 813097.0,
        "i": 810971.0,
        "t": "1"
    },
    {
        "a": "2024",
        "g": "M",
        "op": "c",
        "c": "0090",
        "p": 1183404.0,
        "d": 922857.0,
        "i": 842162.0,
        "t": "1"
    },
    {
        "a": "2024",
        "g": "M",
        "op": "c",
        "c": "0101",
        "p": 2752129.0,
        "d": 2401740.0,
        "i": 2393103.0,
        "t": "1"
    },
    {
        "a": "2024",
        "g": "M",
        "op": "c",
        "c": "0117",
        "p": 88218.0,
        "d": 67735.0,
        "i": 49828.0,
        "t": "1"
    },
    {
        "a": "2024",
        "g": "M",
        "op": "c",
        "c": "0132",
        "p": 1083834.0,
        "d": 399764.0,
        "i": 368809.0,
        "t": "1"
    },
    {
        "a": "2024",
        "g": "M",
        "op": "c",
        "c": "0138",
        "p": 1212842.0,
        "d": 0.0,
        "i": 0.0,
        "t": "1"
    },
    {
        "a": "2024",
        "g": "M",
        "op": "c",
        "c": "0140",
        "p": 385139.0,
        "d": 363441.0,
        "i": 363441.0,
        "t": "1"
    },
    {
        "a": "2024",
        "g": "M",
        "op": "c",
        "c": "0142",
        "p": 23861.0,
        "d": 7814.0,
        "i": 5340.0,
        "t": "1"
    },
    {
        "a": "2024",
        "g": "M",
        "op": "c",
        "c": "0146",
        "p": 6635106.0,
        "d": 3790386.0,
        "i": 3706345.0,
        "t": "1"
    },
    {
        "a": "2024",
        "g": "M",
        "op": "c",
        "c": "0148",
        "p": 3745846.0,
        "d": 894153.0,
        "i": 859787.0,
        "t": "1"
    },
    {
        "a": "2024",
        "g": "M",
        "op": "f",
        "c": "03",
        "p": 10273533.0,
        "d": 7816840.0,
        "i": 6951605.0,
        "t": "1"
    },
    {
        "a": "2024",
        "g": "M",
        "op": "f",
        "c": "05",
        "p": 612067.0,
        "d": 495242.0,
        "i": 449673.0,
        "t": "1"
    },
    {
        "a": "2024",
        "g": "M",
        "op": "f",
        "c": "08",
        "p": 463879.0,
        "d": 340440.0,
        "i": 286821.0,
        "t": "1"
    },
    {
        "a": "2024",
        "g": "M",
        "op": "f",
        "c": "10",
        "p": 4209186.0,
        "d": 2361339.0,
        "i": 2359213.0,
        "t": "1"
    },
    {
        "a": "2024",
        "g": "M",
        "op": "c",
        "c": "1001",
        "p": 111712.0,
        "d": 95762.0,
        "i": 93231.0,
        "t": "1"
    },
    {
        "a": "2024",
        "g": "M",
        "op": "f",
        "c": "12",
        "p": 0.0,
        "d": 0.0,
        "i": 0.0,
        "t": "1"
    },
    {
        "a": "2024",
        "g": "M",
        "op": "f",
        "c": "15",
        "p": 6046299.0,
        "d": 1523725.0,
        "i": 1342764.0,
        "t": "1"
    },
    {
        "a": "2024",
        "g": "M",
        "op": "f",
        "c": "17",
        "p": 831904.0,
        "d": 666352.0,
        "i": 556377.0,
        "t": "1"
    },
    {
        "a": "2024",
        "g": "M",
        "op": "f",
        "c": "18",
        "p": 7023607.0,
        "d": 3089727.0,
        "i": 2733127.0,
        "t": "1"
    },
    {
        "a": "2024",
        "g": "M",
        "op": "f",
        "c": "19",
        "p": 6688219.0,
        "d": 3796570.0,
        "i": 3712530.0,
        "t": "1"
    },
    {
        "a": "2024",
        "g": "M",
        "op": "f",
        "c": "20",
        "p": 155430.0,
        "d": 127540.0,
        "i": 119608.0,
        "t": "1"
    },
    {
        "a": "2024",
        "g": "M",
        "op": "f",
        "c": "21",
        "p": 4750881.0,
        "d": 3313187.0,
        "i": 3267095.0,
        "t": "1"
    },
    {
        "a": "2024",
        "g": "M",
        "op": "f",
        "c": "22",
        "p": 1485924.0,
        "d": 1126654.0,
        "i": 1031899.0,
        "t": "1"
    },
    {
        "a": "2024",
        "g": "M",
        "op": "f",
        "c": "23",
        "p": 1374858.0,
        "d": 1270711.0,
        "i": 1149827.0,
        "t": "1"
    },
    {
        "a": "2024",
        "g": "M",
        "op": "f",
        "c": "24",
        "p": 14072.0,
        "d": 9804.0,
        "i": 9804.0,
        "t": "1"
    },
    {
        "a": "2024",
        "g": "M",
        "op": "c",
        "c": "9001",
        "p": 5428791.0,
        "d": 3840675.0,
        "i": 3485704.0,
        "t": "1"
    },
    {
        "a": "2024",
        "g": "M",
        "op": "c",
        "c": "9002",
        "p": 9070776.0,
        "d": 6900713.0,
        "i": 5993692.0,
        "t": "1"
    },
    {
        "a": "2024",
        "g": "M",
        "op": "c",
        "c": "0042",
        "p": 2855805.0,
        "d": 1548243.0,
        "i": 1548243.0,
        "t": "2"
    },
    {
        "a": "2024",
        "g": "M",
        "op": "c",
        "c": "0046",
        "p": 0.0,
        "d": 0.0,
        "i": 0.0,
        "t": "2"
    },
    {
        "a": "2024",
        "g": "M",
        "op": "c",
        "c": "0083",
        "p": 6526822.0,
        "d": 2716983.0,
        "i": 2451801.0,
        "t": "2"
    },
    {
        "a": "2024",
        "g": "M",
        "op": "c",
        "c": "0089",
        "p": 1353381.0,
        "d": 813097.0,
        "i": 810971.0,
        "t": "2"
    },
    {
        "a": "2024",
        "g": "M",
        "op": "c",
        "c": "0090",
        "p": 1183404.0,
        "d": 922857.0,
        "i": 842162.0,
        "t": "2"
    },
    {
        "a": "2024",
        "g": "M",
        "op": "c",
        "c": "0101",
        "p": 2752129.0,
        "d": 2401740.0,
        "i": 2393103.0,
        "t": "2"
    },
    {
        "a": "2024",
        "g": "M",
        "op": "c",
        "c": "0132",
        "p": 1083834.0,
        "d": 399764.0,
        "i": 368809.0,
        "t": "2"
    },
    {
        "a": "2024",
        "g": "M",
        "op": "c",
        "c": "0138",
        "p": 1212842.0,
        "d": 0.0,
        "i": 0.0,
        "t": "2"
    },
    {
        "a": "2024",
        "g": "M",
        "op": "c",
        "c": "0140",
        "p": 385139.0,
        "d": 363441.0,
        "i": 363441.0,
        "t": "2"
    },
    {
        "a": "2024",
        "g": "M",
        "op": "c",
        "c": "0146",
        "p": 6635106.0,
        "d": 3790386.0,
        "i": 3706345.0,
        "t": "2"
    },
    {
        "a": "2024",
        "g": "M",
        "op": "c",
        "c": "0148",
        "p": 3745846.0,
        "d": 894153.0,
        "i": 859787.0,
        "t": "2"
    },
    {
        "a": "2024",
        "g": "M",
        "op": "f",
        "c": "03",
        "p": 1132980.0,
        "d": 836882.0,
        "i": 697382.0,
        "t": "2"
    },
    {
        "a": "2024",
        "g": "M",
        "op": "f",
        "c": "10",
        "p": 4209186.0,
        "d": 2361339.0,
        "i": 2359213.0,
        "t": "2"
    },
    {
        "a": "2024",
        "g": "M",
        "op": "f",
        "c": "12",
        "p": 0.0,
        "d": 0.0,
        "i": 0.0,
        "t": "2"
    },
    {
        "a": "2024",
        "g": "M",
        "op": "f",
        "c": "15",
        "p": 4958688.0,
        "d": 894153.0,
        "i": 859787.0,
        "t": "2"
    },
    {
        "a": "2024",
        "g": "M",
        "op": "f",
        "c": "18",
        "p": 6526822.0,
        "d": 2716983.0,
        "i": 2451801.0,
        "t": "2"
    },
    {
        "a": "2024",
        "g": "M",
        "op": "f",
        "c": "19",
        "p": 6635106.0,
        "d": 3790386.0,
        "i": 3706345.0,
        "t": "2"
    },
    {
        "a": "2024",
        "g": "M",
        "op": "f",
        "c": "21",
        "p": 4221102.0,
        "d": 3164944.0,
        "i": 3125353.0,
        "t": "2"
    },
    {
        "a": "2024",
        "g": "M",
        "op": "f",
        "c": "22",
        "p": 1183404.0,
        "d": 922857.0,
        "i": 842162.0,
        "t": "2"
    },
    {
        "a": "2024",
        "g": "M",
        "op": "c",
        "c": "9001",
        "p": 0.0,
        "d": 0.0,
        "i": 0.0,
        "t": "2"
    },
    {
        "a": "2024",
        "g": "M",
        "op": "c",
        "c": "9002",
        "p": 1132980.0,
        "d": 836882.0,
        "i": 697382.0,
        "t": "2"
    },
    {
        "a": "2024",
        "g": "M",
        "op": "c",
        "c": "0002",
        "p": 43718.0,
        "d": 31778.0,
        "i": 26378.0,
        "t": "3"
    },
    {
        "a": "2024",
        "g": "M",
        "op": "c",
        "c": "0030",
        "p": 373849.0,
        "d": 322824.0,
        "i": 312056.0,
        "t": "3"
    },
    {
        "a": "2024",
        "g": "M",
        "op": "c",
        "c": "0036",
        "p": 382494.0,
        "d": 298395.0,
        "i": 277527.0,
        "t": "3"
    },
    {
        "a": "2024",
        "g": "M",
        "op": "c",
        "c": "0068",
        "p": 306707.0,
        "d": 226713.0,
        "i": 171286.0,
        "t": "3"
    },
    {
        "a": "2024",
        "g": "M",
        "op": "c",
        "c": "0083",
        "p": 365425.0,
        "d": 295060.0,
        "i": 210641.0,
        "t": "3"
    },
    {
        "a": "2024",
        "g": "M",
        "op": "c",
        "c": "0117",
        "p": 88218.0,
        "d": 67735.0,
        "i": 49828.0,
        "t": "3"
    },
    {
        "a": "2024",
        "g": "M",
        "op": "c",
        "c": "0142",
        "p": 23861.0,
        "d": 7814.0,
        "i": 5340.0,
        "t": "3"
    },
    {
        "a": "2024",
        "g": "M",
        "op": "f",
        "c": "03",
        "p": 9140553.0,
        "d": 6979958.0,
        "i": 6254223.0,
        "t": "3"
    },
    {
        "a": "2024",
        "g": "M",
        "op": "f",
        "c": "05",
        "p": 612067.0,
        "d": 495242.0,
        "i": 449673.0,
        "t": "3"
    },
    {
        "a": "2024",
        "g": "M",
        "op": "f",
        "c": "08",
        "p": 463879.0,
        "d": 340440.0,
        "i": 286821.0,
        "t": "3"
    },
    {
        "a": "2024",
        "g": "M",
        "op": "c",
        "c": "1001",
        "p": 111712.0,
        "d": 95762.0,
        "i": 93231.0,
        "t": "3"
    },
    {
        "a": "2024",
        "g": "M",
        "op": "f",
        "c": "15",
        "p": 1087611.0,
        "d": 629572.0,
        "i": 482977.0,
        "t": "3"
    },
    {
        "a": "2024",
        "g": "M",
        "op": "f",
        "c": "17",
        "p": 831904.0,
        "d": 666352.0,
        "i": 556377.0,
        "t": "3"
    },
    {
        "a": "2024",
        "g": "M",
        "op": "f",
        "c": "18",
        "p": 496785.0,
        "d": 372744.0,
        "i": 281325.0,
        "t": "3"
    },
    {
        "a": "2024",
        "g": "M",
        "op": "f",
        "c": "19",
        "p": 53113.0,
        "d": 6185.0,
        "i": 6185.0,
        "t": "3"
    },
    {
        "a": "2024",
        "g": "M",
        "op": "f",
        "c": "20",
        "p": 155430.0,
        "d": 127540.0,
        "i": 119608.0,
        "t": "3"
    },
    {
        "a": "2024",
        "g": "M",
        "op": "f",
        "c": "21",
        "p": 529779.0,
        "d": 148242.0,
        "i": 141742.0,
        "t": "3"
    },
    {
        "a": "2024",
        "g": "M",
        "op": "f",
        "c": "22",
        "p": 302520.0,
        "d": 203797.0,
        "i": 189737.0,
        "t": "3"
    },
    {
        "a": "2024",
        "g": "M",
        "op": "f",
        "c": "23",
        "p": 1374858.0,
        "d": 1270711.0,
        "i": 1149827.0,
        "t": "3"
    },
    {
        "a": "2024",
        "g": "M",
        "op": "f",
        "c": "24",
        "p": 14072.0,
        "d": 9804.0,
        "i": 9804.0,
        "t": "3"
    },
    {
        "a": "2024",
        "g": "M",
        "op": "c",
        "c": "9001",
        "p": 5428791.0,
        "d": 3840675.0,
        "i": 3485704.0,
        "t": "3"
    },
    {
        "a": "2024",
        "g": "M",
        "op": "c",
        "c": "9002",
        "p": 7937796.0,
        "d": 6063831.0,
        "i": 5296310.0,
        "t": "3"
    }
]