[
    {
        "a": "2024",
        "g": "M",
        "op": "c",
        "c": "0002",
        "p": 12534.0,
        "d": 390.0,
        "i": 390.0,
        "t": "1"
    },
    {
        "a": "2024",
        "g": "M",
        "op": "c",
        "c": "0030",
        "p": 0.0,
        "d": 0.0,
        "i": 0.0,
        "t": "1"
    },
    {
        "a": "2024",
        "g": "M",
        "op": "c",
        "c": "0036",
        "p": 20000.0,
        "d": 20000.0,
        "i": 20000.0,
        "t": "1"
    },
    {
        "a": "2024",
        "g": "M",
        "op": "c",
        "c": "0068",
        "p": 6000.0,
        "d": 6000.0,
        "i": 6000.0,
        "t": "1"
    },
    {
        "a": "2024",
        "g": "M",
        "op": "c",
        "c": "0083",
        "p": 26827.0,
        "d": 20050.0,
        "i": 20050.0,
        "t": "1"
    },
    {
        "a": "2024",
        "g": "M",
        "op": "c",
        "c": "0101",
        "p": 36602.0,
        "d": 32454.0,
        "i": 32454.0,
        "t": "1"
    },
    {
        "a": "2024",
        "g": "M",
        "op": "c",
        "c": "0109",
        "p": 10000.0,
        "d": 10000.0,
        "i": 10000.0,
        "t": "1"
    },
    {
        "a": "2024",
        "g": "M",
        "op": "c",
        "c": "0132",
        "p": 5026.0,
        "d": 5025.0,
        "i": 5025.0,
        "t": "1"
    },
    {
        "a": "2024",
        "g": "M",
        "op": "c",
        "c": "0138",
        "p": 94419.0,
        "d": 8000.0,
        "i": 8000.0,
        "t": "1"
    },
    {
        "a": "2024",
        "g": "M",
        "op": "c",
        "c": "0148",
        "p": 198056.0,
        "d": 192806.0,
        "i": 192806.0,
        "t": "1"
    },
    {
        "a": "2024",
        "g": "M",
        "op": "f",
        "c": "03",
        "p": 932975.0,
        "d": 702524.0,
        "i": 700124.0,
        "t": "1"
    },
    {
        "a": "2024",
        "g": "M",
        "op": "f",
        "c": "05",
        "p": 6000.0,
        "d": 6000.0,
        "i": 6000.0,
        "t": "1"
    },
    {
        "a": "2024",
        "g": "M",
        "op": "f",
        "c": "07",
        "p": 407192.0,
        "d": 404650.0,
        "i": 342816.0,
        "t": "1"
    },
    {
        "a": "2024",
        "g": "M",
        "op": "f",
        "c": "10",
        "p": 115709.0,
        "d": 101646.0,
        "i": 101646.0,
        "t": "1"
    },
    {
        "a": "2024",
        "g": "M",
        "op": "c",
        "c": "1001",
        "p": 3360.0,
        "d": 3360.0,
        "i": 3360.0,
        "t": "1"
    },
    {
        "a": "2024",
        "g": "M",
        "op": "f",
        "c": "15",
        "p": 292475.0,
        "d": 200806.0,
        "i": 200806.0,
        "t": "1"
    },
    {
        "a": "2024",
        "g": "M",
        "op": "f",
        "c": "17",
        "p": 20000.0,
        "d": 20000.0,
        "i": 20000.0,
        "t": "1"
    },
    {
        "a": "2024",
        "g": "M",
        "op": "f",
        "c": "18",
        "p": 85481.0,
        "d": 68701.0,
        "i": 68701.0,
        "t": "1"
    },
    {
        "a": "2024",
        "g": "M",
        "op": "f",
        "c": "19",
        "p": 76340.0,
        "d": 50904.0,
        "i": 49704.0,
        "t": "1"
    },
    {
        "a": "2024",
        "g": "M",
        "op": "f",
        "c": "20",
        "p": 47955.0,
        "d": 35811.0,
        "i": 35811.0,
        "t": "1"
    },
    {
        "a": "2024",
        "g": "M",
        "op": "f",
        "c": "21",
        "p": 379859.0,
        "d": 98708.0,
        "i": 98708.0,
        "t": "1"
    },
    {
        "a": "2024",
        "g": "M",
        "op": "f",
        "c": "22",
        "p": 0.0,
        "d": 0.0,
        "i": 0.0,
        "t": "1"
    },
    {
        "a": "2024",
        "g": "M",
        "op": "f",
        "c": "23",
        "p": 97245.0,
        "d": 91328.0,
        "i": 91328.0,
        "t": "1"
    },
    {
        "a": "2024",
        "g": "M",
        "op": "f",
        "c": "24",
        "p": 10564.0,
        "d": 10564.0,
        "i": 10564.0,
        "t": "1"
    },
    {
        "a": "2024",
        "g": "M",
        "op": "c",
        "c": "9001",
        "p": 614083.0,
        "d": 557945.0,
        "i": 555545.0,
        "t": "1"
    },
    {
        "a": "2024",
        "g": "M",
        "op": "c",
        "c": "9002",
        "p": 1444888.0,
        "d": 935611.0,
        "i": 872577.0,
        "t": "1"
    },
    {
        "a": "2024",
        "g": "M",
        "op": "c",
        "c": "0002",
        "p": 10000.0,
        "d": 0.0,
        "i": 0.0,
        "t": "2"
    },
    {
        "a": "2024",
        "g": "M",
        "op": "c",
        "c": "0101",
        "p": 36602.0,
        "d": 32454.0,
        "i": 32454.0,
        "t": "2"
    },
    {
        "a": "2024",
        "g": "M",
        "op": "c",
        "c": "0109",
        "p": 10000.0,
        "d": 10000.0,
        "i": 10000.0,
        "t": "2"
    },
    {
        "a": "2024",
        "g": "M",
        "op": "c",
        "c": "0132",
        "p": 5026.0,
        "d": 5025.0,
        "i": 5025.0,
        "t": "2"
    },
    {
        "a": "2024",
        "g": "M",
        "op": "c",
        "c": "0138",
        "p": 94419.0,
        "d": 8000.0,
        "i": 8000.0,
        "t": "2"
    },
    {
        "a": "2024",
        "g": "M",
        "op": "c",
        "c": "0148",
        "p": 198056.0,
        "d": 192806.0,
        "i": 192806.0,
        "t": "2"
    },
    {
        "a": "2024",
        "g": "M",
        "op": "f",
        "c": "03",
        "p": 171603.0,
        "d": 10000.0,
        "i": 10000.0,
        "t": "2"
    },
    {
        "a": "2024",
        "g": "M",
        "op": "f",
        "c": "10",
        "p": 115709.0,
        "d": 101646.0,
        "i": 101646.0,
        "t": "2"
    },
    {
        "a": "2024",
        "g": "M",
        "op": "f",
        "c": "15",
        "p": 292475.0,
        "d": 200806.0,
        "i": 200806.0,
        "t": "2"
    },
    {
        "a": "2024",
        "g": "M",
        "op": "f",
        "c": "19",
        "p": 30000.0,
        "d": 10000.0,
        "i": 10000.0,
        "t": "2"
    },
    {
        "a": "2024",
        "g": "M",
        "op": "f",
        "c": "20",
        "p": 42061.0,
        "d": 32061.0,
        "i": 32061.0,
        "t": "2"
    },
    {
        "a": "2024",
        "g": "M",
        "op": "f",
        "c": "21",
        "p": 326631.0,
        "d": 45480.0,
        "i": 45480.0,
        "t": "2"
    },
    {
        "a": "2024",
        "g": "M",
        "op": "c",
        "c": "9002",
        "p": 624376.0,
        "d": 151707.0,
        "i": 151707.0,
        "t": "2"
    },
    {
        "a": "2024",
        "g": "M",
        "op": "c",
        "c": "0002",
        "p": 2534.0,
        "d": 390.0,
        "i": 390.0,
        "t": "3"
    },
    {
        "a": "2024",
        "g": "M",
        "op": "c",
        "c": "0030",
        "p": 0.0,
        "d": 0.0,
        "i": 0.0,
        "t": "3"
    },
    {
        "a": "2024",
        "g": "M",
        "op": "c",
        "c": "0036",
        "p": 20000.0,
        "d": 20000.0,
        "i": 20000.0,
        "t": "3"
    },
    {
        "a": "2024",
        "g": "M",
        "op": "c",
        "c": "0068",
        "p": 6000.0,
        "d": 6000.0,
        "i": 6000.0,
        "t": "3"
    },
    {
        "a": "2024",
        "g": "M",
        "op": "c",
        "c": "0083",
        "p": 26827.0,
        "d": 20050.0,
        "i": 20050.0,
        "t": "3"
    },
    {
        "a": "2024",
        "g": "M",
        "op": "f",
        "c": "03",
        "p": 761372.0,
        "d": 692524.0,
        "i": 690124.0,
        "t": "3"
    },
    {
        "a": "2024",
        "g": "M",
        "op": "f",
        "c": "05",
        "p": 6000.0,
        "d": 6000.0,
        "i": 6000.0,
        "t": "3"
    },
    {
        "a": "2024",
        "g": "M",
        "op": "f",
        "c": "07",
        "p": 407192.0,
        "d": 404650.0,
        "i": 342816.0,
        "t": "3"
    },
    {
        "a": "2024",
        "g": "M",
        "op": "c",
        "c": "1001",
        "p": 3360.0,
        "d": 3360.0,
        "i": 3360.0,
        "t": "3"
    },
    {
        "a": "2024",
        "g": "M",
        "op": "f",
        "c": "17",
        "p": 20000.0,
        "d": 20000.0,
        "i": 20000.0,
        "t": "3"
    },
    {
        "a": "2024",
        "g": "M",
        "op": "f",
        "c": "18",
        "p": 85481.0,
        "d": 68701.0,
        "i": 68701.0,
        "t": "3"
    },
    {
        "a": "2024",
        "g": "M",
        "op": "f",
        "c": "19",
        "p": 46340.0,
        "d": 40904.0,
        "i": 39704.0,
        "t": "3"
    },
    {
        "a": "2024",
        "g": "M",
        "op": "f",
        "c": "20",
        "p": 5894.0,
        "d": 3750.0,
        "i": 3750.0,
        "t": "3"
    },
    {
        "a": "2024",
        "g": "M",
        "op": "f",
        "c": "21",
        "p": 53228.0,
        "d": 53228.0,
        "i": 53228.0,
        "t": "3"
    },
    {
        "a": "2024",
        "g": "M",
        "op": "f",
        "c": "22",
        "p": 0.0,
        "d": 0.0,
        "i": 0.0,
        "t": "3"
    },
    {
        "a": "2024",
        "g": "M",
        "op": "f",
        "c": "23",
        "p": 97245.0,
        "d": 91328.0,
        "i": 91328.0,
        "t": "3"
    },
    {
        "a": "2024",
        "g": "M",
        "op": "f",
        "c": "24",
        "p": 10564.0,
        "d": 10564.0,
        "i": 10564.0,
        "t": "3"
    },
    {
        "a": "2024",
        "g": "M",
        "op": "c",
        "c": "9001",
        "p": 614083.0,
        "d": 557945.0,
        "i": 555545.0,
        "t": "3"
    },
    {
        "a": "2024",
        "g": "M",
        "op": "c",
        "c": "9002",
        "p": 820512.0,
        "d": 783905.0,
        "i": 720871.0,
        "t": "3"
    }
]