[
    {
        "a": "2024",
        "g": "M",
        "op": "c",
        "c": "0030",
        "p": 8000.0,
        "d": 0.0,
        "i": 0.0,
        "t": "1"
    },
    {
        "a": "2024",
        "g": "M",
        "op": "c",
        "c": "0036",
        "p": 34000.0,
        "d": 31000.0,
        "i": 31000.0,
        "t": "1"
    },
    {
        "a": "2024",
        "g": "M",
        "op": "c",
        "c": "0042",
        "p": 12106.0,
        "d": 3500.0,
        "i": 3500.0,
        "t": "1"
    },
    {
        "a": "2024",
        "g": "M",
        "op": "c",
        "c": "0068",
        "p": 19744.0,
        "d": 15580.0,
        "i": 15580.0,
        "t": "1"
    },
    {
        "a": "2024",
        "g": "M",
        "op": "c",
        "c": "0083",
        "p": 115100.0,
        "d": 14403.0,
        "i": 14403.0,
        "t": "1"
    },
    {
        "a": "2024",
        "g": "M",
        "op": "c",
        "c": "0090",
        "p": 98020.0,
        "d": 66124.0,
        "i": 66124.0,
        "t": "1"
    },
    {
        "a": "2024",
        "g": "M",
        "op": "c",
        "c": "0138",
        "p": 1409104.0,
        "d": 118243.0,
        "i": 118243.0,
        "t": "1"
    },
    {
        "a": "2024",
        "g": "M",
        "op": "c",
        "c": "0142",
        "p": 5400.0,
        "d": 2130.0,
        "i": 2130.0,
        "t": "1"
    },
    {
        "a": "2024",
        "g": "M",
        "op": "c",
        "c": "0146",
        "p": 8142596.0,
        "d": 1179155.0,
        "i": 1179155.0,
        "t": "1"
    },
    {
        "a": "2024",
        "g": "M",
        "op": "f",
        "c": "03",
        "p": 1372573.0,
        "d": 1286331.0,
        "i": 1282029.0,
        "t": "1"
    },
    {
        "a": "2024",
        "g": "M",
        "op": "f",
        "c": "05",
        "p": 19744.0,
        "d": 8300.0,
        "i": 8300.0,
        "t": "1"
    },
    {
        "a": "2024",
        "g": "M",
        "op": "f",
        "c": "07",
        "p": 311060.0,
        "d": 273300.0,
        "i": 273300.0,
        "t": "1"
    },
    {
        "a": "2024",
        "g": "M",
        "op": "f",
        "c": "10",
        "p": 64200.0,
        "d": 3500.0,
        "i": 3500.0,
        "t": "1"
    },
    {
        "a": "2024",
        "g": "M",
        "op": "f",
        "c": "15",
        "p": 1409104.0,
        "d": 118243.0,
        "i": 118243.0,
        "t": "1"
    },
    {
        "a": "2024",
        "g": "M",
        "op": "f",
        "c": "17",
        "p": 34000.0,
        "d": 31000.0,
        "i": 31000.0,
        "t": "1"
    },
    {
        "a": "2024",
        "g": "M",
        "op": "f",
        "c": "18",
        "p": 115100.0,
        "d": 14403.0,
        "i": 14403.0,
        "t": "1"
    },
    {
        "a": "2024",
        "g": "M",
        "op": "f",
        "c": "19",
        "p": 8153596.0,
        "d": 1179155.0,
        "i": 1179155.0,
        "t": "1"
    },
    {
        "a": "2024",
        "g": "M",
        "op": "f",
        "c": "22",
        "p": 101520.0,
        "d": 68924.0,
        "i": 68924.0,
        "t": "1"
    },
    {
        "a": "2024",
        "g": "M",
        "op": "f",
        "c": "23",
        "p": 103802.0,
        "d": 92021.0,
        "i": 92021.0,
        "t": "1"
    },
    {
        "a": "2024",
        "g": "M",
        "op": "f",
        "c": "24",
        "p": 12580.0,
        "d": 6790.0,
        "i": 6790.0,
        "t": "1"
    },
    {
        "a": "2024",
        "g": "M",
        "op": "f",
        "c": "25",
        "p": 497502.0,
        "d": 497057.0,
        "i": 497057.0,
        "t": "1"
    },
    {
        "a": "2024",
        "g": "M",
        "op": "c",
        "c": "9001",
        "p": 652316.0,
        "d": 600759.0,
        "i": 596457.0,
        "t": "1"
    },
    {
        "a": "2024",
        "g": "M",
        "op": "c",
        "c": "9002",
        "p": 1698395.0,
        "d": 1548130.0,
        "i": 1548130.0,
        "t": "1"
    },
    {
        "a": "2024",
        "g": "M",
        "op": "c",
        "c": "0042",
        "p": 12106.0,
        "d": 3500.0,
        "i": 3500.0,
        "t": "2"
    },
    {
        "a": "2024",
        "g": "M",
        "op": "c",
        "c": "0083",
        "p": 97258.0,
        "d": 0.0,
        "i": 0.0,
        "t": "2"
    },
    {
        "a": "2024",
        "g": "M",
        "op": "c",
        "c": "0090",
        "p": 98020.0,
        "d": 66124.0,
        "i": 66124.0,
        "t": "2"
    },
    {
        "a": "2024",
        "g": "M",
        "op": "c",
        "c": "0138",
        "p": 1308360.0,
        "d": 25000.0,
        "i": 25000.0,
        "t": "2"
    },
    {
        "a": "2024",
        "g": "M",
        "op": "c",
        "c": "0146",
        "p": 8142596.0,
        "d": 1179155.0,
        "i": 1179155.0,
        "t": "2"
    },
    {
        "a": "2024",
        "g": "M",
        "op": "f",
        "c": "03",
        "p": 698931.0,
        "d": 676572.0,
        "i": 676572.0,
        "t": "2"
    },
    {
        "a": "2024",
        "g": "M",
        "op": "f",
        "c": "10",
        "p": 64200.0,
        "d": 3500.0,
        "i": 3500.0,
        "t": "2"
    },
    {
        "a": "2024",
        "g": "M",
        "op": "f",
        "c": "15",
        "p": 1308360.0,
        "d": 25000.0,
        "i": 25000.0,
        "t": "2"
    },
    {
        "a": "2024",
        "g": "M",
        "op": "f",
        "c": "18",
        "p": 97258.0,
        "d": 0.0,
        "i": 0.0,
        "t": "2"
    },
    {
        "a": "2024",
        "g": "M",
        "op": "f",
        "c": "19",
        "p": 8142596.0,
        "d": 1179155.0,
        "i": 1179155.0,
        "t": "2"
    },
    {
        "a": "2024",
        "g": "M",
        "op": "f",
        "c": "22",
        "p": 98020.0,
        "d": 66124.0,
        "i": 66124.0,
        "t": "2"
    },
    {
        "a": "2024",
        "g": "M",
        "op": "c",
        "c": "9002",
        "p": 751025.0,
        "d": 676572.0,
        "i": 676572.0,
        "t": "2"
    },
    {
        "a": "2024",
        "g": "M",
        "op": "c",
        "c": "0030",
        "p": 8000.0,
        "d": 0.0,
        "i": 0.0,
        "t": "3"
    },
    {
        "a": "2024",
        "g": "M",
        "op": "c",
        "c": "0036",
        "p": 34000.0,
        "d": 31000.0,
        "i": 31000.0,
        "t": "3"
    },
    {
        "a": "2024",
        "g": "M",
        "op": "c",
        "c": "0068",
        "p": 19744.0,
        "d": 15580.0,
        "i": 15580.0,
        "t": "3"
    },
    {
        "a": "2024",
        "g": "M",
        "op": "c",
        "c": "0083",
        "p": 17842.0,
        "d": 14403.0,
        "i": 14403.0,
        "t": "3"
    },
    {
        "a": "2024",
        "g": "M",
        "op": "c",
        "c": "0138",
        "p": 100744.0,
        "d": 93243.0,
        "i": 93243.0,
        "t": "3"
    },
    {
        "a": "2024",
        "g": "M",
        "op": "c",
        "c": "0142",
        "p": 5400.0,
        "d": 2130.0,
        "i": 2130.0,
        "t": "3"
    },
    {
        "a": "2024",
        "g": "M",
        "op": "f",
        "c": "03",
        "p": 673642.0,
        "d": 609759.0,
        "i": 605457.0,
        "t": "3"
    },
    {
        "a": "2024",
        "g": "M",
        "op": "f",
        "c": "05",
        "p": 19744.0,
        "d": 8300.0,
        "i": 8300.0,
        "t": "3"
    },
    {
        "a": "2024",
        "g": "M",
        "op": "f",
        "c": "07",
        "p": 311060.0,
        "d": 273300.0,
        "i": 273300.0,
        "t": "3"
    },
    {
        "a": "2024",
        "g": "M",
        "op": "f",
        "c": "15",
        "p": 100744.0,
        "d": 93243.0,
        "i": 93243.0,
        "t": "3"
    },
    {
        "a": "2024",
        "g": "M",
        "op": "f",
        "c": "17",
        "p": 34000.0,
        "d": 31000.0,
        "i": 31000.0,
        "t": "3"
    },
    {
        "a": "2024",
        "g": "M",
        "op": "f",
        "c": "18",
        "p": 17842.0,
        "d": 14403.0,
        "i": 14403.0,
        "t": "3"
    },
    {
        "a": "2024",
        "g": "M",
        "op": "f",
        "c": "19",
        "p": 11000.0,
        "d": 0.0,
        "i": 0.0,
        "t": "3"
    },
    {
        "a": "2024",
        "g": "M",
        "op": "f",
        "c": "22",
        "p": 3500.0,
        "d": 2800.0,
        "i": 2800.0,
        "t": "3"
    },
    {
        "a": "2024",
        "g": "M",
        "op": "f",
        "c": "23",
        "p": 103802.0,
        "d": 92021.0,
        "i": 92021.0,
        "t": "3"
    },
    {
        "a": "2024",
        "g": "M",
        "op": "f",
        "c": "24",
        "p": 12580.0,
        "d": 6790.0,
        "i": 6790.0,
        "t": "3"
    },
    {
        "a": "2024",
        "g": "M",
        "op": "f",
        "c": "25",
        "p": 497502.0,
        "d": 497057.0,
        "i": 497057.0,
        "t": "3"
    },
    {
        "a": "2024",
        "g": "M",
        "op": "c",
        "c": "9001",
        "p": 652316.0,
        "d": 600759.0,
        "i": 596457.0,
        "t": "3"
    },
    {
        "a": "2024",
        "g": "M",
        "op": "c",
        "c": "9002",
        "p": 947370.0,
        "d": 871559.0,
        "i": 871559.0,
        "t": "3"
    }
]