[
    {
        "a": "2024",
        "g": "M",
        "op": "c",
        "c": "0030",
        "p": 217238.0,
        "d": 195774.0,
        "i": 185430.0,
        "t": "1"
    },
    {
        "a": "2024",
        "g": "M",
        "op": "c",
        "c": "0036",
        "p": 308893.0,
        "d": 295365.0,
        "i": 284841.0,
        "t": "1"
    },
    {
        "a": "2024",
        "g": "M",
        "op": "c",
        "c": "0042",
        "p": 2232388.0,
        "d": 0.0,
        "i": 0.0,
        "t": "1"
    },
    {
        "a": "2024",
        "g": "M",
        "op": "c",
        "c": "0068",
        "p": 176234.0,
        "d": 44985.0,
        "i": 30512.0,
        "t": "1"
    },
    {
        "a": "2024",
        "g": "M",
        "op": "c",
        "c": "0082",
        "p": 18950.0,
        "d": 0.0,
        "i": 0.0,
        "t": "1"
    },
    {
        "a": "2024",
        "g": "M",
        "op": "c",
        "c": "0083",
        "p": 138836.0,
        "d": 89322.0,
        "i": 82168.0,
        "t": "1"
    },
    {
        "a": "2024",
        "g": "M",
        "op": "c",
        "c": "0090",
        "p": 51000.0,
        "d": 10000.0,
        "i": 10000.0,
        "t": "1"
    },
    {
        "a": "2024",
        "g": "M",
        "op": "c",
        "c": "0101",
        "p": 189144.0,
        "d": 149143.0,
        "i": 149143.0,
        "t": "1"
    },
    {
        "a": "2024",
        "g": "M",
        "op": "c",
        "c": "0138",
        "p": 8449432.0,
        "d": 2354728.0,
        "i": 2354728.0,
        "t": "1"
    },
    {
        "a": "2024",
        "g": "M",
        "op": "c",
        "c": "0142",
        "p": 16188.0,
        "d": 15578.0,
        "i": 15153.0,
        "t": "1"
    },
    {
        "a": "2024",
        "g": "M",
        "op": "c",
        "c": "0146",
        "p": 3451103.0,
        "d": 3164435.0,
        "i": 3134935.0,
        "t": "1"
    },
    {
        "a": "2024",
        "g": "M",
        "op": "c",
        "c": "0148",
        "p": 151860.0,
        "d": 124736.0,
        "i": 124736.0,
        "t": "1"
    },
    {
        "a": "2024",
        "g": "M",
        "op": "c",
        "c": "0150",
        "p": 35000.0,
        "d": 35000.0,
        "i": 35000.0,
        "t": "1"
    },
    {
        "a": "2024",
        "g": "M",
        "op": "f",
        "c": "03",
        "p": 4852753.0,
        "d": 3632831.0,
        "i": 3412149.0,
        "t": "1"
    },
    {
        "a": "2024",
        "g": "M",
        "op": "f",
        "c": "05",
        "p": 293701.0,
        "d": 211170.0,
        "i": 197550.0,
        "t": "1"
    },
    {
        "a": "2024",
        "g": "M",
        "op": "f",
        "c": "07",
        "p": 332690.0,
        "d": 172677.0,
        "i": 121874.0,
        "t": "1"
    },
    {
        "a": "2024",
        "g": "M",
        "op": "f",
        "c": "09",
        "p": 19885.0,
        "d": 19884.0,
        "i": 19884.0,
        "t": "1"
    },
    {
        "a": "2024",
        "g": "M",
        "op": "f",
        "c": "10",
        "p": 2297608.0,
        "d": 57360.0,
        "i": 57360.0,
        "t": "1"
    },
    {
        "a": "2024",
        "g": "M",
        "op": "f",
        "c": "15",
        "p": 8653756.0,
        "d": 2526098.0,
        "i": 2526098.0,
        "t": "1"
    },
    {
        "a": "2024",
        "g": "M",
        "op": "f",
        "c": "17",
        "p": 322801.0,
        "d": 308646.0,
        "i": 298121.0,
        "t": "1"
    },
    {
        "a": "2024",
        "g": "M",
        "op": "f",
        "c": "18",
        "p": 157786.0,
        "d": 89322.0,
        "i": 82168.0,
        "t": "1"
    },
    {
        "a": "2024",
        "g": "M",
        "op": "f",
        "c": "19",
        "p": 3701145.0,
        "d": 3378407.0,
        "i": 3326651.0,
        "t": "1"
    },
    {
        "a": "2024",
        "g": "M",
        "op": "f",
        "c": "21",
        "p": 262376.0,
        "d": 182721.0,
        "i": 180421.0,
        "t": "1"
    },
    {
        "a": "2024",
        "g": "M",
        "op": "f",
        "c": "22",
        "p": 215020.0,
        "d": 172032.0,
        "i": 164616.0,
        "t": "1"
    },
    {
        "a": "2024",
        "g": "M",
        "op": "f",
        "c": "23",
        "p": 532260.0,
        "d": 346593.0,
        "i": 300975.0,
        "t": "1"
    },
    {
        "a": "2024",
        "g": "M",
        "op": "f",
        "c": "25",
        "p": 537939.0,
        "d": 429691.0,
        "i": 0.0,
        "t": "1"
    },
    {
        "a": "2024",
        "g": "M",
        "op": "c",
        "c": "9001",
        "p": 2158697.0,
        "d": 1901486.0,
        "i": 1782384.0,
        "t": "1"
    },
    {
        "a": "2024",
        "g": "M",
        "op": "c",
        "c": "9002",
        "p": 4584757.0,
        "d": 3146880.0,
        "i": 2498838.0,
        "t": "1"
    },
    {
        "a": "2024",
        "g": "M",
        "op": "c",
        "c": "0036",
        "p": 39600.0,
        "d": 39500.0,
        "i": 39500.0,
        "t": "2"
    },
    {
        "a": "2024",
        "g": "M",
        "op": "c",
        "c": "0042",
        "p": 2232388.0,
        "d": 0.0,
        "i": 0.0,
        "t": "2"
    },
    {
        "a": "2024",
        "g": "M",
        "op": "c",
        "c": "0068",
        "p": 115696.0,
        "d": 0.0,
        "i": 0.0,
        "t": "2"
    },
    {
        "a": "2024",
        "g": "M",
        "op": "c",
        "c": "0082",
        "p": 18950.0,
        "d": 0.0,
        "i": 0.0,
        "t": "2"
    },
    {
        "a": "2024",
        "g": "M",
        "op": "c",
        "c": "0083",
        "p": 40000.0,
        "d": 0.0,
        "i": 0.0,
        "t": "2"
    },
    {
        "a": "2024",
        "g": "M",
        "op": "c",
        "c": "0090",
        "p": 51000.0,
        "d": 10000.0,
        "i": 10000.0,
        "t": "2"
    },
    {
        "a": "2024",
        "g": "M",
        "op": "c",
        "c": "0101",
        "p": 189144.0,
        "d": 149143.0,
        "i": 149143.0,
        "t": "2"
    },
    {
        "a": "2024",
        "g": "M",
        "op": "c",
        "c": "0138",
        "p": 8449432.0,
        "d": 2354728.0,
        "i": 2354728.0,
        "t": "2"
    },
    {
        "a": "2024",
        "g": "M",
        "op": "c",
        "c": "0146",
        "p": 3451103.0,
        "d": 3164435.0,
        "i": 3134935.0,
        "t": "2"
    },
    {
        "a": "2024",
        "g": "M",
        "op": "c",
        "c": "0148",
        "p": 151860.0,
        "d": 124736.0,
        "i": 124736.0,
        "t": "2"
    },
    {
        "a": "2024",
        "g": "M",
        "op": "c",
        "c": "0150",
        "p": 35000.0,
        "d": 35000.0,
        "i": 35000.0,
        "t": "2"
    },
    {
        "a": "2024",
        "g": "M",
        "op": "f",
        "c": "03",
        "p": 2338249.0,
        "d": 1461319.0,
        "i": 1383993.0,
        "t": "2"
    },
    {
        "a": "2024",
        "g": "M",
        "op": "f",
        "c": "05",
        "p": 58155.0,
        "d": 0.0,
        "i": 0.0,
        "t": "2"
    },
    {
        "a": "2024",
        "g": "M",
        "op": "f",
        "c": "10",
        "p": 2297608.0,
        "d": 57360.0,
        "i": 57360.0,
        "t": "2"
    },
    {
        "a": "2024",
        "g": "M",
        "op": "f",
        "c": "15",
        "p": 8640656.0,
        "d": 2514648.0,
        "i": 2514648.0,
        "t": "2"
    },
    {
        "a": "2024",
        "g": "M",
        "op": "f",
        "c": "17",
        "p": 39600.0,
        "d": 39500.0,
        "i": 39500.0,
        "t": "2"
    },
    {
        "a": "2024",
        "g": "M",
        "op": "f",
        "c": "18",
        "p": 58950.0,
        "d": 0.0,
        "i": 0.0,
        "t": "2"
    },
    {
        "a": "2024",
        "g": "M",
        "op": "f",
        "c": "19",
        "p": 3482964.0,
        "d": 3196296.0,
        "i": 3166796.0,
        "t": "2"
    },
    {
        "a": "2024",
        "g": "M",
        "op": "f",
        "c": "21",
        "p": 221144.0,
        "d": 149143.0,
        "i": 149143.0,
        "t": "2"
    },
    {
        "a": "2024",
        "g": "M",
        "op": "f",
        "c": "22",
        "p": 86000.0,
        "d": 45000.0,
        "i": 45000.0,
        "t": "2"
    },
    {
        "a": "2024",
        "g": "M",
        "op": "f",
        "c": "23",
        "p": 115696.0,
        "d": 0.0,
        "i": 0.0,
        "t": "2"
    },
    {
        "a": "2024",
        "g": "M",
        "op": "c",
        "c": "9002",
        "p": 2564849.0,
        "d": 1585723.0,
        "i": 1508397.0,
        "t": "2"
    },
    {
        "a": "2024",
        "g": "M",
        "op": "c",
        "c": "0030",
        "p": 217238.0,
        "d": 195774.0,
        "i": 185430.0,
        "t": "3"
    },
    {
        "a": "2024",
        "g": "M",
        "op": "c",
        "c": "0036",
        "p": 269293.0,
        "d": 255865.0,
        "i": 245341.0,
        "t": "3"
    },
    {
        "a": "2024",
        "g": "M",
        "op": "c",
        "c": "0068",
        "p": 60538.0,
        "d": 44985.0,
        "i": 30512.0,
        "t": "3"
    },
    {
        "a": "2024",
        "g": "M",
        "op": "c",
        "c": "0083",
        "p": 98836.0,
        "d": 89322.0,
        "i": 82168.0,
        "t": "3"
    },
    {
        "a": "2024",
        "g": "M",
        "op": "c",
        "c": "0142",
        "p": 16188.0,
        "d": 15578.0,
        "i": 15153.0,
        "t": "3"
    },
    {
        "a": "2024",
        "g": "M",
        "op": "f",
        "c": "03",
        "p": 2514504.0,
        "d": 2171513.0,
        "i": 2028156.0,
        "t": "3"
    },
    {
        "a": "2024",
        "g": "M",
        "op": "f",
        "c": "05",
        "p": 235546.0,
        "d": 211170.0,
        "i": 197550.0,
        "t": "3"
    },
    {
        "a": "2024",
        "g": "M",
        "op": "f",
        "c": "07",
        "p": 332690.0,
        "d": 172677.0,
        "i": 121874.0,
        "t": "3"
    },
    {
        "a": "2024",
        "g": "M",
        "op": "f",
        "c": "09",
        "p": 19885.0,
        "d": 19884.0,
        "i": 19884.0,
        "t": "3"
    },
    {
        "a": "2024",
        "g": "M",
        "op": "f",
        "c": "15",
        "p": 13100.0,
        "d": 11451.0,
        "i": 11451.0,
        "t": "3"
    },
    {
        "a": "2024",
        "g": "M",
        "op": "f",
        "c": "17",
        "p": 283201.0,
        "d": 269146.0,
        "i": 258621.0,
        "t": "3"
    },
    {
        "a": "2024",
        "g": "M",
        "op": "f",
        "c": "18",
        "p": 98836.0,
        "d": 89322.0,
        "i": 82168.0,
        "t": "3"
    },
    {
        "a": "2024",
        "g": "M",
        "op": "f",
        "c": "19",
        "p": 218181.0,
        "d": 182111.0,
        "i": 159855.0,
        "t": "3"
    },
    {
        "a": "2024",
        "g": "M",
        "op": "f",
        "c": "21",
        "p": 41232.0,
        "d": 33578.0,
        "i": 31278.0,
        "t": "3"
    },
    {
        "a": "2024",
        "g": "M",
        "op": "f",
        "c": "22",
        "p": 129020.0,
        "d": 127032.0,
        "i": 119616.0,
        "t": "3"
    },
    {
        "a": "2024",
        "g": "M",
        "op": "f",
        "c": "23",
        "p": 416564.0,
        "d": 346593.0,
        "i": 300975.0,
        "t": "3"
    },
    {
        "a": "2024",
        "g": "M",
        "op": "f",
        "c": "25",
        "p": 537939.0,
        "d": 429691.0,
        "i": 0.0,
        "t": "3"
    },
    {
        "a": "2024",
        "g": "M",
        "op": "c",
        "c": "9001",
        "p": 2158697.0,
        "d": 1901486.0,
        "i": 1782384.0,
        "t": "3"
    },
    {
        "a": "2024",
        "g": "M",
        "op": "c",
        "c": "9002",
        "p": 2019908.0,
        "d": 1561158.0,
        "i": 990440.0,
        "t": "3"
    }
]