[
    {
        "a": "2024",
        "g": "M",
        "op": "c",
        "c": "0002",
        "p": 2055.0,
        "d": 1800.0,
        "i": 1600.0,
        "t": "1"
    },
    {
        "a": "2024",
        "g": "M",
        "op": "c",
        "c": "0030",
        "p": 37766.0,
        "d": 36239.0,
        "i": 30510.0,
        "t": "1"
    },
    {
        "a": "2024",
        "g": "M",
        "op": "c",
        "c": "0036",
        "p": 161259.0,
        "d": 149836.0,
        "i": 149836.0,
        "t": "1"
    },
    {
        "a": "2024",
        "g": "M",
        "op": "c",
        "c": "0039",
        "p": 193340.0,
        "d": 12697.0,
        "i": 12697.0,
        "t": "1"
    },
    {
        "a": "2024",
        "g": "M",
        "op": "c",
        "c": "0040",
        "p": 0.0,
        "d": 0.0,
        "i": 0.0,
        "t": "1"
    },
    {
        "a": "2024",
        "g": "M",
        "op": "c",
        "c": "0068",
        "p": 13750.0,
        "d": 6050.0,
        "i": 6050.0,
        "t": "1"
    },
    {
        "a": "2024",
        "g": "M",
        "op": "c",
        "c": "0083",
        "p": 45001.0,
        "d": 43032.0,
        "i": 43032.0,
        "t": "1"
    },
    {
        "a": "2024",
        "g": "M",
        "op": "c",
        "c": "0101",
        "p": 26500.0,
        "d": 26500.0,
        "i": 26500.0,
        "t": "1"
    },
    {
        "a": "2024",
        "g": "M",
        "op": "c",
        "c": "0121",
        "p": 40000.0,
        "d": 0.0,
        "i": 0.0,
        "t": "1"
    },
    {
        "a": "2024",
        "g": "M",
        "op": "c",
        "c": "0138",
        "p": 675842.0,
        "d": 321290.0,
        "i": 321290.0,
        "t": "1"
    },
    {
        "a": "2024",
        "g": "M",
        "op": "c",
        "c": "0146",
        "p": 38000.0,
        "d": 15200.0,
        "i": 15200.0,
        "t": "1"
    },
    {
        "a": "2024",
        "g": "M",
        "op": "c",
        "c": "0148",
        "p": 187469.0,
        "d": 30297.0,
        "i": 30297.0,
        "t": "1"
    },
    {
        "a": "2024",
        "g": "M",
        "op": "f",
        "c": "03",
        "p": 1863574.0,
        "d": 1532514.0,
        "i": 1509881.0,
        "t": "1"
    },
    {
        "a": "2024",
        "g": "M",
        "op": "f",
        "c": "05",
        "p": 37766.0,
        "d": 36239.0,
        "i": 30510.0,
        "t": "1"
    },
    {
        "a": "2024",
        "g": "M",
        "op": "f",
        "c": "07",
        "p": 212922.0,
        "d": 195398.0,
        "i": 195398.0,
        "t": "1"
    },
    {
        "a": "2024",
        "g": "M",
        "op": "f",
        "c": "10",
        "p": 424934.0,
        "d": 146501.0,
        "i": 146501.0,
        "t": "1"
    },
    {
        "a": "2024",
        "g": "M",
        "op": "c",
        "c": "1001",
        "p": 20290.0,
        "d": 11609.0,
        "i": 10929.0,
        "t": "1"
    },
    {
        "a": "2024",
        "g": "M",
        "op": "f",
        "c": "15",
        "p": 863311.0,
        "d": 351586.0,
        "i": 351586.0,
        "t": "1"
    },
    {
        "a": "2024",
        "g": "M",
        "op": "f",
        "c": "17",
        "p": 161259.0,
        "d": 149836.0,
        "i": 149836.0,
        "t": "1"
    },
    {
        "a": "2024",
        "g": "M",
        "op": "f",
        "c": "18",
        "p": 45001.0,
        "d": 43032.0,
        "i": 43032.0,
        "t": "1"
    },
    {
        "a": "2024",
        "g": "M",
        "op": "f",
        "c": "19",
        "p": 38000.0,
        "d": 15200.0,
        "i": 15200.0,
        "t": "1"
    },
    {
        "a": "2024",
        "g": "M",
        "op": "f",
        "c": "20",
        "p": 22345.0,
        "d": 13409.0,
        "i": 12529.0,
        "t": "1"
    },
    {
        "a": "2024",
        "g": "M",
        "op": "f",
        "c": "21",
        "p": 104385.0,
        "d": 99555.0,
        "i": 99555.0,
        "t": "1"
    },
    {
        "a": "2024",
        "g": "M",
        "op": "f",
        "c": "23",
        "p": 131335.0,
        "d": 111240.0,
        "i": 109012.0,
        "t": "1"
    },
    {
        "a": "2024",
        "g": "M",
        "op": "c",
        "c": "9001",
        "p": 1027150.0,
        "d": 898476.0,
        "i": 875843.0,
        "t": "1"
    },
    {
        "a": "2024",
        "g": "M",
        "op": "c",
        "c": "9002",
        "p": 1436410.0,
        "d": 1141485.0,
        "i": 1139257.0,
        "t": "1"
    },
    {
        "a": "2024",
        "g": "M",
        "op": "c",
        "c": "0036",
        "p": 114284.0,
        "d": 106270.0,
        "i": 106270.0,
        "t": "2"
    },
    {
        "a": "2024",
        "g": "M",
        "op": "c",
        "c": "0039",
        "p": 180640.0,
        "d": 0.0,
        "i": 0.0,
        "t": "2"
    },
    {
        "a": "2024",
        "g": "M",
        "op": "c",
        "c": "0121",
        "p": 40000.0,
        "d": 0.0,
        "i": 0.0,
        "t": "2"
    },
    {
        "a": "2024",
        "g": "M",
        "op": "c",
        "c": "0138",
        "p": 632824.0,
        "d": 280332.0,
        "i": 280332.0,
        "t": "2"
    },
    {
        "a": "2024",
        "g": "M",
        "op": "c",
        "c": "0146",
        "p": 38000.0,
        "d": 15200.0,
        "i": 15200.0,
        "t": "2"
    },
    {
        "a": "2024",
        "g": "M",
        "op": "c",
        "c": "0148",
        "p": 187469.0,
        "d": 30297.0,
        "i": 30297.0,
        "t": "2"
    },
    {
        "a": "2024",
        "g": "M",
        "op": "f",
        "c": "03",
        "p": 732784.0,
        "d": 561772.0,
        "i": 561772.0,
        "t": "2"
    },
    {
        "a": "2024",
        "g": "M",
        "op": "f",
        "c": "10",
        "p": 398484.0,
        "d": 127754.0,
        "i": 127754.0,
        "t": "2"
    },
    {
        "a": "2024",
        "g": "M",
        "op": "f",
        "c": "15",
        "p": 820293.0,
        "d": 310629.0,
        "i": 310629.0,
        "t": "2"
    },
    {
        "a": "2024",
        "g": "M",
        "op": "f",
        "c": "17",
        "p": 114284.0,
        "d": 106270.0,
        "i": 106270.0,
        "t": "2"
    },
    {
        "a": "2024",
        "g": "M",
        "op": "f",
        "c": "19",
        "p": 38000.0,
        "d": 15200.0,
        "i": 15200.0,
        "t": "2"
    },
    {
        "a": "2024",
        "g": "M",
        "op": "f",
        "c": "23",
        "p": 0.0,
        "d": 0.0,
        "i": 0.0,
        "t": "2"
    },
    {
        "a": "2024",
        "g": "M",
        "op": "c",
        "c": "9002",
        "p": 910628.0,
        "d": 689526.0,
        "i": 689526.0,
        "t": "2"
    },
    {
        "a": "2024",
        "g": "M",
        "op": "c",
        "c": "0002",
        "p": 2055.0,
        "d": 1800.0,
        "i": 1600.0,
        "t": "3"
    },
    {
        "a": "2024",
        "g": "M",
        "op": "c",
        "c": "0030",
        "p": 37766.0,
        "d": 36239.0,
        "i": 30510.0,
        "t": "3"
    },
    {
        "a": "2024",
        "g": "M",
        "op": "c",
        "c": "0036",
        "p": 46975.0,
        "d": 43566.0,
        "i": 43566.0,
        "t": "3"
    },
    {
        "a": "2024",
        "g": "M",
        "op": "c",
        "c": "0039",
        "p": 12700.0,
        "d": 12697.0,
        "i": 12697.0,
        "t": "3"
    },
    {
        "a": "2024",
        "g": "M",
        "op": "c",
        "c": "0040",
        "p": 0.0,
        "d": 0.0,
        "i": 0.0,
        "t": "3"
    },
    {
        "a": "2024",
        "g": "M",
        "op": "c",
        "c": "0068",
        "p": 13750.0,
        "d": 6050.0,
        "i": 6050.0,
        "t": "3"
    },
    {
        "a": "2024",
        "g": "M",
        "op": "c",
        "c": "0083",
        "p": 45001.0,
        "d": 43032.0,
        "i": 43032.0,
        "t": "3"
    },
    {
        "a": "2024",
        "g": "M",
        "op": "c",
        "c": "0101",
        "p": 26500.0,
        "d": 26500.0,
        "i": 26500.0,
        "t": "3"
    },
    {
        "a": "2024",
        "g": "M",
        "op": "c",
        "c": "0138",
        "p": 43018.0,
        "d": 40958.0,
        "i": 40958.0,
        "t": "3"
    },
    {
        "a": "2024",
        "g": "M",
        "op": "f",
        "c": "03",
        "p": 1130790.0,
        "d": 970742.0,
        "i": 948109.0,
        "t": "3"
    },
    {
        "a": "2024",
        "g": "M",
        "op": "f",
        "c": "05",
        "p": 37766.0,
        "d": 36239.0,
        "i": 30510.0,
        "t": "3"
    },
    {
        "a": "2024",
        "g": "M",
        "op": "f",
        "c": "07",
        "p": 212922.0,
        "d": 195398.0,
        "i": 195398.0,
        "t": "3"
    },
    {
        "a": "2024",
        "g": "M",
        "op": "f",
        "c": "10",
        "p": 26450.0,
        "d": 18747.0,
        "i": 18747.0,
        "t": "3"
    },
    {
        "a": "2024",
        "g": "M",
        "op": "c",
        "c": "1001",
        "p": 20290.0,
        "d": 11609.0,
        "i": 10929.0,
        "t": "3"
    },
    {
        "a": "2024",
        "g": "M",
        "op": "f",
        "c": "15",
        "p": 43018.0,
        "d": 40958.0,
        "i": 40958.0,
        "t": "3"
    },
    {
        "a": "2024",
        "g": "M",
        "op": "f",
        "c": "17",
        "p": 46975.0,
        "d": 43566.0,
        "i": 43566.0,
        "t": "3"
    },
    {
        "a": "2024",
        "g": "M",
        "op": "f",
        "c": "18",
        "p": 45001.0,
        "d": 43032.0,
        "i": 43032.0,
        "t": "3"
    },
    {
        "a": "2024",
        "g": "M",
        "op": "f",
        "c": "20",
        "p": 22345.0,
        "d": 13409.0,
        "i": 12529.0,
        "t": "3"
    },
    {
        "a": "2024",
        "g": "M",
        "op": "f",
        "c": "21",
        "p": 104385.0,
        "d": 99555.0,
        "i": 99555.0,
        "t": "3"
    },
    {
        "a": "2024",
        "g": "M",
        "op": "f",
        "c": "23",
        "p": 131335.0,
        "d": 111240.0,
        "i": 109012.0,
        "t": "3"
    },
    {
        "a": "2024",
        "g": "M",
        "op": "c",
        "c": "9001",
        "p": 1027150.0,
        "d": 898476.0,
        "i": 875843.0,
        "t": "3"
    },
    {
        "a": "2024",
        "g": "M",
        "op": "c",
        "c": "9002",
        "p": 525782.0,
        "d": 451959.0,
        "i": 449731.0,
        "t": "3"
    }
]