[
    {
        "a": "2024",
        "g": "R",
        "op": "c",
        "c": "0002",
        "p": 69855029.0,
        "d": 67593974.0,
        "i": 66595847.0,
        "t": "1"
    },
    {
        "a": "2024",
        "g": "R",
        "op": "c",
        "c": "0016",
        "p": 21919226.0,
        "d": 21400297.0,
        "i": 21166068.0,
        "t": "1"
    },
    {
        "a": "2024",
        "g": "R",
        "op": "c",
        "c": "0017",
        "p": 9381983.0,
        "d": 9173373.0,
        "i": 9087900.0,
        "t": "1"
    },
    {
        "a": "2024",
        "g": "R",
        "op": "c",
        "c": "0018",
        "p": 30258543.0,
        "d": 29497665.0,
        "i": 28974626.0,
        "t": "1"
    },
    {
        "a": "2024",
        "g": "R",
        "op": "c",
        "c": "0024",
        "p": 13945705.0,
        "d": 13326551.0,
        "i": 13135414.0,
        "t": "1"
    },
    {
        "a": "2024",
        "g": "R",
        "op": "c",
        "c": "0030",
        "p": 5285095.0,
        "d": 5080512.0,
        "i": 5080512.0,
        "t": "1"
    },
    {
        "a": "2024",
        "g": "R",
        "op": "c",
        "c": "0042",
        "p": 73027925.0,
        "d": 47190145.0,
        "i": 42624094.0,
        "t": "1"
    },
    {
        "a": "2024",
        "g": "R",
        "op": "c",
        "c": "0046",
        "p": 738659.0,
        "d": 77220.0,
        "i": 77220.0,
        "t": "1"
    },
    {
        "a": "2024",
        "g": "R",
        "op": "c",
        "c": "0048",
        "p": 358756.0,
        "d": 145769.0,
        "i": 145769.0,
        "t": "1"
    },
    {
        "a": "2024",
        "g": "R",
        "op": "c",
        "c": "0051",
        "p": 1228744.0,
        "d": 1134191.0,
        "i": 1130941.0,
        "t": "1"
    },
    {
        "a": "2024",
        "g": "R",
        "op": "c",
        "c": "0057",
        "p": 155447.0,
        "d": 135600.0,
        "i": 135600.0,
        "t": "1"
    },
    {
        "a": "2024",
        "g": "R",
        "op": "c",
        "c": "0068",
        "p": 8484128.0,
        "d": 7918181.0,
        "i": 7808072.0,
        "t": "1"
    },
    {
        "a": "2024",
        "g": "R",
        "op": "c",
        "c": "0082",
        "p": 11120051.0,
        "d": 4953776.0,
        "i": 4933226.0,
        "t": "1"
    },
    {
        "a": "2024",
        "g": "R",
        "op": "c",
        "c": "0083",
        "p": 41466719.0,
        "d": 20489948.0,
        "i": 19400251.0,
        "t": "1"
    },
    {
        "a": "2024",
        "g": "R",
        "op": "c",
        "c": "0090",
        "p": 835270300.0,
        "d": 782994703.0,
        "i": 774827225.0,
        "t": "1"
    },
    {
        "a": "2024",
        "g": "R",
        "op": "c",
        "c": "0103",
        "p": 1581226.0,
        "d": 1191977.0,
        "i": 1135281.0,
        "t": "1"
    },
    {
        "a": "2024",
        "g": "R",
        "op": "c",
        "c": "0104",
        "p": 39371055.0,
        "d": 24625158.0,
        "i": 24293446.0,
        "t": "1"
    },
    {
        "a": "2024",
        "g": "R",
        "op": "c",
        "c": "0106",
        "p": 12529294.0,
        "d": 11434723.0,
        "i": 11308880.0,
        "t": "1"
    },
    {
        "a": "2024",
        "g": "R",
        "op": "c",
        "c": "0107",
        "p": 1648226.0,
        "d": 987867.0,
        "i": 957406.0,
        "t": "1"
    },
    {
        "a": "2024",
        "g": "R",
        "op": "c",
        "c": "0116",
        "p": 947192.0,
        "d": 376027.0,
        "i": 267897.0,
        "t": "1"
    },
    {
        "a": "2024",
        "g": "R",
        "op": "c",
        "c": "0121",
        "p": 50780.0,
        "d": 50780.0,
        "i": 50780.0,
        "t": "1"
    },
    {
        "a": "2024",
        "g": "R",
        "op": "c",
        "c": "0126",
        "p": 544600.0,
        "d": 332134.0,
        "i": 286361.0,
        "t": "1"
    },
    {
        "a": "2024",
        "g": "R",
        "op": "c",
        "c": "0127",
        "p": 0.0,
        "d": 0.0,
        "i": 0.0,
        "t": "1"
    },
    {
        "a": "2024",
        "g": "R",
        "op": "c",
        "c": "0129",
        "p": 2786022.0,
        "d": 2667478.0,
        "i": 2639816.0,
        "t": "1"
    },
    {
        "a": "2024",
        "g": "R",
        "op": "c",
        "c": "0131",
        "p": 14506856.0,
        "d": 14108796.0,
        "i": 13979311.0,
        "t": "1"
    },
    {
        "a": "2024",
        "g": "R",
        "op": "c",
        "c": "0138",
        "p": 116197878.0,
        "d": 68677462.0,
        "i": 58257911.0,
        "t": "1"
    },
    {
        "a": "2024",
        "g": "R",
        "op": "c",
        "c": "0147",
        "p": 25843072.0,
        "d": 20569819.0,
        "i": 19609559.0,
        "t": "1"
    },
    {
        "a": "2024",
        "g": "R",
        "op": "c",
        "c": "0148",
        "p": 87446201.0,
        "d": 49855259.0,
        "i": 41779580.0,
        "t": "1"
    },
    {
        "a": "2024",
        "g": "R",
        "op": "c",
        "c": "0150",
        "p": 162300.0,
        "d": 109721.0,
        "i": 107803.0,
        "t": "1"
    },
    {
        "a": "2024",
        "g": "R",
        "op": "f",
        "c": "03",
        "p": 155756212.0,
        "d": 54267819.0,
        "i": 53060393.0,
        "t": "1"
    },
    {
        "a": "2024",
        "g": "R",
        "op": "f",
        "c": "05",
        "p": 8654621.0,
        "d": 7897818.0,
        "i": 7861324.0,
        "t": "1"
    },
    {
        "a": "2024",
        "g": "R",
        "op": "f",
        "c": "07",
        "p": 2701384.0,
        "d": 1736323.0,
        "i": 1569672.0,
        "t": "1"
    },
    {
        "a": "2024",
        "g": "R",
        "op": "f",
        "c": "08",
        "p": 960897.0,
        "d": 732045.0,
        "i": 729405.0,
        "t": "1"
    },
    {
        "a": "2024",
        "g": "R",
        "op": "f",
        "c": "09",
        "p": 1366431.0,
        "d": 1074033.0,
        "i": 1062873.0,
        "t": "1"
    },
    {
        "a": "2024",
        "g": "R",
        "op": "f",
        "c": "10",
        "p": 101439880.0,
        "d": 72464235.0,
        "i": 66127532.0,
        "t": "1"
    },
    {
        "a": "2024",
        "g": "R",
        "op": "c",
        "c": "1001",
        "p": 85958529.0,
        "d": 82402369.0,
        "i": 80518927.0,
        "t": "1"
    },
    {
        "a": "2024",
        "g": "R",
        "op": "c",
        "c": "1002",
        "p": 102486.0,
        "d": 101191.0,
        "i": 101191.0,
        "t": "1"
    },
    {
        "a": "2024",
        "g": "R",
        "op": "f",
        "c": "11",
        "p": 1905104.0,
        "d": 1648333.0,
        "i": 1605385.0,
        "t": "1"
    },
    {
        "a": "2024",
        "g": "R",
        "op": "f",
        "c": "12",
        "p": 1776253.0,
        "d": 1077549.0,
        "i": 1043569.0,
        "t": "1"
    },
    {
        "a": "2024",
        "g": "R",
        "op": "f",
        "c": "13",
        "p": 544600.0,
        "d": 332134.0,
        "i": 286361.0,
        "t": "1"
    },
    {
        "a": "2024",
        "g": "R",
        "op": "f",
        "c": "14",
        "p": 1667470.0,
        "d": 1080255.0,
        "i": 714605.0,
        "t": "1"
    },
    {
        "a": "2024",
        "g": "R",
        "op": "f",
        "c": "15",
        "p": 205609323.0,
        "d": 120304083.0,
        "i": 101546854.0,
        "t": "1"
    },
    {
        "a": "2024",
        "g": "R",
        "op": "f",
        "c": "16",
        "p": 5248788.0,
        "d": 611348.0,
        "i": 543068.0,
        "t": "1"
    },
    {
        "a": "2024",
        "g": "R",
        "op": "f",
        "c": "17",
        "p": 612811.0,
        "d": 135600.0,
        "i": 135600.0,
        "t": "1"
    },
    {
        "a": "2024",
        "g": "R",
        "op": "f",
        "c": "18",
        "p": 52725849.0,
        "d": 25570658.0,
        "i": 24460410.0,
        "t": "1"
    },
    {
        "a": "2024",
        "g": "R",
        "op": "f",
        "c": "19",
        "p": 1786191.0,
        "d": 1597866.0,
        "i": 1572066.0,
        "t": "1"
    },
    {
        "a": "2024",
        "g": "R",
        "op": "f",
        "c": "20",
        "p": 732179862.0,
        "d": 676026965.0,
        "i": 662148840.0,
        "t": "1"
    },
    {
        "a": "2024",
        "g": "R",
        "op": "f",
        "c": "21",
        "p": 1857489.0,
        "d": 1825324.0,
        "i": 1825324.0,
        "t": "1"
    },
    {
        "a": "2024",
        "g": "R",
        "op": "f",
        "c": "22",
        "p": 1050432330.0,
        "d": 970678295.0,
        "i": 959294713.0,
        "t": "1"
    },
    {
        "a": "2024",
        "g": "R",
        "op": "f",
        "c": "23",
        "p": 4767003.0,
        "d": 4720767.0,
        "i": 4604577.0,
        "t": "1"
    },
    {
        "a": "2024",
        "g": "R",
        "op": "f",
        "c": "24",
        "p": 48580000.0,
        "d": 47966150.0,
        "i": 47645948.0,
        "t": "1"
    },
    {
        "a": "2024",
        "g": "R",
        "op": "f",
        "c": "25",
        "p": 18057955.0,
        "d": 16406392.0,
        "i": 16392040.0,
        "t": "1"
    },
    {
        "a": "2024",
        "g": "R",
        "op": "c",
        "c": "9001",
        "p": 230983317.0,
        "d": 212792189.0,
        "i": 209433939.0,
        "t": "1"
    },
    {
        "a": "2024",
        "g": "R",
        "op": "c",
        "c": "9002",
        "p": 655475109.0,
        "d": 506759137.0,
        "i": 494379706.0,
        "t": "1"
    },
    {
        "a": "2024",
        "g": "R",
        "op": "c",
        "c": "0030",
        "p": 5285095.0,
        "d": 5080512.0,
        "i": 5080512.0,
        "t": "2"
    },
    {
        "a": "2024",
        "g": "R",
        "op": "c",
        "c": "0042",
        "p": 73027925.0,
        "d": 47190145.0,
        "i": 42624094.0,
        "t": "2"
    },
    {
        "a": "2024",
        "g": "R",
        "op": "c",
        "c": "0046",
        "p": 738659.0,
        "d": 77220.0,
        "i": 77220.0,
        "t": "2"
    },
    {
        "a": "2024",
        "g": "R",
        "op": "c",
        "c": "0048",
        "p": 358756.0,
        "d": 145769.0,
        "i": 145769.0,
        "t": "2"
    },
    {
        "a": "2024",
        "g": "R",
        "op": "c",
        "c": "0057",
        "p": 155447.0,
        "d": 135600.0,
        "i": 135600.0,
        "t": "2"
    },
    {
        "a": "2024",
        "g": "R",
        "op": "c",
        "c": "0068",
        "p": 1252041.0,
        "d": 1212040.0,
        "i": 1212040.0,
        "t": "2"
    },
    {
        "a": "2024",
        "g": "R",
        "op": "c",
        "c": "0082",
        "p": 11120051.0,
        "d": 4953776.0,
        "i": 4933226.0,
        "t": "2"
    },
    {
        "a": "2024",
        "g": "R",
        "op": "c",
        "c": "0083",
        "p": 39805544.0,
        "d": 19440343.0,
        "i": 18362504.0,
        "t": "2"
    },
    {
        "a": "2024",
        "g": "R",
        "op": "c",
        "c": "0090",
        "p": 135085847.0,
        "d": 99166291.0,
        "i": 98284806.0,
        "t": "2"
    },
    {
        "a": "2024",
        "g": "R",
        "op": "c",
        "c": "0103",
        "p": 125000.0,
        "d": 0.0,
        "i": 0.0,
        "t": "2"
    },
    {
        "a": "2024",
        "g": "R",
        "op": "c",
        "c": "0104",
        "p": 22296133.0,
        "d": 8062444.0,
        "i": 8044037.0,
        "t": "2"
    },
    {
        "a": "2024",
        "g": "R",
        "op": "c",
        "c": "0106",
        "p": 107950.0,
        "d": 107950.0,
        "i": 107950.0,
        "t": "2"
    },
    {
        "a": "2024",
        "g": "R",
        "op": "c",
        "c": "0127",
        "p": 0.0,
        "d": 0.0,
        "i": 0.0,
        "t": "2"
    },
    {
        "a": "2024",
        "g": "R",
        "op": "c",
        "c": "0138",
        "p": 87005061.0,
        "d": 49832125.0,
        "i": 44852970.0,
        "t": "2"
    },
    {
        "a": "2024",
        "g": "R",
        "op": "c",
        "c": "0147",
        "p": 9103709.0,
        "d": 6091646.0,
        "i": 5379610.0,
        "t": "2"
    },
    {
        "a": "2024",
        "g": "R",
        "op": "c",
        "c": "0148",
        "p": 87446201.0,
        "d": 49855259.0,
        "i": 41779580.0,
        "t": "2"
    },
    {
        "a": "2024",
        "g": "R",
        "op": "f",
        "c": "03",
        "p": 89166837.0,
        "d": 7410907.0,
        "i": 7090965.0,
        "t": "2"
    },
    {
        "a": "2024",
        "g": "R",
        "op": "f",
        "c": "05",
        "p": 6549742.0,
        "d": 6091947.0,
        "i": 6091947.0,
        "t": "2"
    },
    {
        "a": "2024",
        "g": "R",
        "op": "f",
        "c": "07",
        "p": 125000.0,
        "d": 0.0,
        "i": 0.0,
        "t": "2"
    },
    {
        "a": "2024",
        "g": "R",
        "op": "f",
        "c": "08",
        "p": 746027.0,
        "d": 712045.0,
        "i": 709405.0,
        "t": "2"
    },
    {
        "a": "2024",
        "g": "R",
        "op": "f",
        "c": "09",
        "p": 1267489.0,
        "d": 986028.0,
        "i": 976628.0,
        "t": "2"
    },
    {
        "a": "2024",
        "g": "R",
        "op": "f",
        "c": "10",
        "p": 83422757.0,
        "d": 56321810.0,
        "i": 50081688.0,
        "t": "2"
    },
    {
        "a": "2024",
        "g": "R",
        "op": "c",
        "c": "1001",
        "p": 19662036.0,
        "d": 18917112.0,
        "i": 18188845.0,
        "t": "2"
    },
    {
        "a": "2024",
        "g": "R",
        "op": "f",
        "c": "11",
        "p": 1651605.0,
        "d": 1411869.0,
        "i": 1375921.0,
        "t": "2"
    },
    {
        "a": "2024",
        "g": "R",
        "op": "f",
        "c": "12",
        "p": 1657587.0,
        "d": 959664.0,
        "i": 927664.0,
        "t": "2"
    },
    {
        "a": "2024",
        "g": "R",
        "op": "f",
        "c": "14",
        "p": 1667470.0,
        "d": 1080255.0,
        "i": 714605.0,
        "t": "2"
    },
    {
        "a": "2024",
        "g": "R",
        "op": "f",
        "c": "15",
        "p": 176416506.0,
        "d": 101458746.0,
        "i": 88141913.0,
        "t": "2"
    },
    {
        "a": "2024",
        "g": "R",
        "op": "f",
        "c": "16",
        "p": 4671939.0,
        "d": 37500.0,
        "i": 37500.0,
        "t": "2"
    },
    {
        "a": "2024",
        "g": "R",
        "op": "f",
        "c": "17",
        "p": 612811.0,
        "d": 135600.0,
        "i": 135600.0,
        "t": "2"
    },
    {
        "a": "2024",
        "g": "R",
        "op": "f",
        "c": "18",
        "p": 50925595.0,
        "d": 24394119.0,
        "i": 23295730.0,
        "t": "2"
    },
    {
        "a": "2024",
        "g": "R",
        "op": "f",
        "c": "20",
        "p": 56104187.0,
        "d": 33355791.0,
        "i": 32230257.0,
        "t": "2"
    },
    {
        "a": "2024",
        "g": "R",
        "op": "f",
        "c": "21",
        "p": 1857489.0,
        "d": 1825324.0,
        "i": 1825324.0,
        "t": "2"
    },
    {
        "a": "2024",
        "g": "R",
        "op": "f",
        "c": "22",
        "p": 151809185.0,
        "d": 112270477.0,
        "i": 110534949.0,
        "t": "2"
    },
    {
        "a": "2024",
        "g": "R",
        "op": "f",
        "c": "23",
        "p": 1212041.0,
        "d": 1212040.0,
        "i": 1212040.0,
        "t": "2"
    },
    {
        "a": "2024",
        "g": "R",
        "op": "c",
        "c": "9002",
        "p": 137288812.0,
        "d": 39395892.0,
        "i": 36173374.0,
        "t": "2"
    },
    {
        "a": "2024",
        "g": "R",
        "op": "c",
        "c": "0002",
        "p": 69855029.0,
        "d": 67593974.0,
        "i": 66595847.0,
        "t": "3"
    },
    {
        "a": "2024",
        "g": "R",
        "op": "c",
        "c": "0016",
        "p": 21919226.0,
        "d": 21400297.0,
        "i": 21166068.0,
        "t": "3"
    },
    {
        "a": "2024",
        "g": "R",
        "op": "c",
        "c": "0017",
        "p": 9381983.0,
        "d": 9173373.0,
        "i": 9087900.0,
        "t": "3"
    },
    {
        "a": "2024",
        "g": "R",
        "op": "c",
        "c": "0018",
        "p": 30258543.0,
        "d": 29497665.0,
        "i": 28974626.0,
        "t": "3"
    },
    {
        "a": "2024",
        "g": "R",
        "op": "c",
        "c": "0024",
        "p": 13945705.0,
        "d": 13326551.0,
        "i": 13135414.0,
        "t": "3"
    },
    {
        "a": "2024",
        "g": "R",
        "op": "c",
        "c": "0051",
        "p": 1228744.0,
        "d": 1134191.0,
        "i": 1130941.0,
        "t": "3"
    },
    {
        "a": "2024",
        "g": "R",
        "op": "c",
        "c": "0068",
        "p": 7232087.0,
        "d": 6706141.0,
        "i": 6596032.0,
        "t": "3"
    },
    {
        "a": "2024",
        "g": "R",
        "op": "c",
        "c": "0083",
        "p": 1661175.0,
        "d": 1049605.0,
        "i": 1037747.0,
        "t": "3"
    },
    {
        "a": "2024",
        "g": "R",
        "op": "c",
        "c": "0090",
        "p": 700184453.0,
        "d": 683828412.0,
        "i": 676542419.0,
        "t": "3"
    },
    {
        "a": "2024",
        "g": "R",
        "op": "c",
        "c": "0103",
        "p": 1456226.0,
        "d": 1191977.0,
        "i": 1135281.0,
        "t": "3"
    },
    {
        "a": "2024",
        "g": "R",
        "op": "c",
        "c": "0104",
        "p": 17074922.0,
        "d": 16562715.0,
        "i": 16249409.0,
        "t": "3"
    },
    {
        "a": "2024",
        "g": "R",
        "op": "c",
        "c": "0106",
        "p": 12421344.0,
        "d": 11326773.0,
        "i": 11200930.0,
        "t": "3"
    },
    {
        "a": "2024",
        "g": "R",
        "op": "c",
        "c": "0107",
        "p": 1648226.0,
        "d": 987867.0,
        "i": 957406.0,
        "t": "3"
    },
    {
        "a": "2024",
        "g": "R",
        "op": "c",
        "c": "0116",
        "p": 947192.0,
        "d": 376027.0,
        "i": 267897.0,
        "t": "3"
    },
    {
        "a": "2024",
        "g": "R",
        "op": "c",
        "c": "0121",
        "p": 50780.0,
        "d": 50780.0,
        "i": 50780.0,
        "t": "3"
    },
    {
        "a": "2024",
        "g": "R",
        "op": "c",
        "c": "0126",
        "p": 544600.0,
        "d": 332134.0,
        "i": 286361.0,
        "t": "3"
    },
    {
        "a": "2024",
        "g": "R",
        "op": "c",
        "c": "0129",
        "p": 2786022.0,
        "d": 2667478.0,
        "i": 2639816.0,
        "t": "3"
    },
    {
        "a": "2024",
        "g": "R",
        "op": "c",
        "c": "0131",
        "p": 14506856.0,
        "d": 14108796.0,
        "i": 13979311.0,
        "t": "3"
    },
    {
        "a": "2024",
        "g": "R",
        "op": "c",
        "c": "0138",
        "p": 29192817.0,
        "d": 18845337.0,
        "i": 13404941.0,
        "t": "3"
    },
    {
        "a": "2024",
        "g": "R",
        "op": "c",
        "c": "0147",
        "p": 16739363.0,
        "d": 14478173.0,
        "i": 14229949.0,
        "t": "3"
    },
    {
        "a": "2024",
        "g": "R",
        "op": "c",
        "c": "0150",
        "p": 162300.0,
        "d": 109721.0,
        "i": 107803.0,
        "t": "3"
    },
    {
        "a": "2024",
        "g": "R",
        "op": "f",
        "c": "03",
        "p": 66589375.0,
        "d": 46856912.0,
        "i": 45969428.0,
        "t": "3"
    },
    {
        "a": "2024",
        "g": "R",
        "op": "f",
        "c": "05",
        "p": 2104879.0,
        "d": 1805871.0,
        "i": 1769377.0,
        "t": "3"
    },
    {
        "a": "2024",
        "g": "R",
        "op": "f",
        "c": "07",
        "p": 2576384.0,
        "d": 1736323.0,
        "i": 1569672.0,
        "t": "3"
    },
    {
        "a": "2024",
        "g": "R",
        "op": "f",
        "c": "08",
        "p": 214870.0,
        "d": 20000.0,
        "i": 20000.0,
        "t": "3"
    },
    {
        "a": "2024",
        "g": "R",
        "op": "f",
        "c": "09",
        "p": 98942.0,
        "d": 88004.0,
        "i": 86244.0,
        "t": "3"
    },
    {
        "a": "2024",
        "g": "R",
        "op": "f",
        "c": "10",
        "p": 18017123.0,
        "d": 16142425.0,
        "i": 16045843.0,
        "t": "3"
    },
    {
        "a": "2024",
        "g": "R",
        "op": "c",
        "c": "1001",
        "p": 66296493.0,
        "d": 63485257.0,
        "i": 62330082.0,
        "t": "3"
    },
    {
        "a": "2024",
        "g": "R",
        "op": "c",
        "c": "1002",
        "p": 102486.0,
        "d": 101191.0,
        "i": 101191.0,
        "t": "3"
    },
    {
        "a": "2024",
        "g": "R",
        "op": "f",
        "c": "11",
        "p": 253499.0,
        "d": 236465.0,
        "i": 229465.0,
        "t": "3"
    },
    {
        "a": "2024",
        "g": "R",
        "op": "f",
        "c": "12",
        "p": 118666.0,
        "d": 117885.0,
        "i": 115905.0,
        "t": "3"
    },
    {
        "a": "2024",
        "g": "R",
        "op": "f",
        "c": "13",
        "p": 544600.0,
        "d": 332134.0,
        "i": 286361.0,
        "t": "3"
    },
    {
        "a": "2024",
        "g": "R",
        "op": "f",
        "c": "15",
        "p": 29192817.0,
        "d": 18845337.0,
        "i": 13404941.0,
        "t": "3"
    },
    {
        "a": "2024",
        "g": "R",
        "op": "f",
        "c": "16",
        "p": 576849.0,
        "d": 573848.0,
        "i": 505568.0,
        "t": "3"
    },
    {
        "a": "2024",
        "g": "R",
        "op": "f",
        "c": "18",
        "p": 1800254.0,
        "d": 1176539.0,
        "i": 1164680.0,
        "t": "3"
    },
    {
        "a": "2024",
        "g": "R",
        "op": "f",
        "c": "19",
        "p": 1786191.0,
        "d": 1597866.0,
        "i": 1572066.0,
        "t": "3"
    },
    {
        "a": "2024",
        "g": "R",
        "op": "f",
        "c": "20",
        "p": 676075675.0,
        "d": 642671174.0,
        "i": 629918582.0,
        "t": "3"
    },
    {
        "a": "2024",
        "g": "R",
        "op": "f",
        "c": "22",
        "p": 898623145.0,
        "d": 858407818.0,
        "i": 848759764.0,
        "t": "3"
    },
    {
        "a": "2024",
        "g": "R",
        "op": "f",
        "c": "23",
        "p": 3554962.0,
        "d": 3508727.0,
        "i": 3392537.0,
        "t": "3"
    },
    {
        "a": "2024",
        "g": "R",
        "op": "f",
        "c": "24",
        "p": 48580000.0,
        "d": 47966150.0,
        "i": 47645948.0,
        "t": "3"
    },
    {
        "a": "2024",
        "g": "R",
        "op": "f",
        "c": "25",
        "p": 18057955.0,
        "d": 16406392.0,
        "i": 16392040.0,
        "t": "3"
    },
    {
        "a": "2024",
        "g": "R",
        "op": "c",
        "c": "9001",
        "p": 230983317.0,
        "d": 212792189.0,
        "i": 209433939.0,
        "t": "3"
    },
    {
        "a": "2024",
        "g": "R",
        "op": "c",
        "c": "9002",
        "p": 518186297.0,
        "d": 467363245.0,
        "i": 458206332.0,
        "t": "3"
    }
]